fastapi_http_exceptions/__init__.py
fastapi_http_exceptions/http_exceptions.py
fastapi_http_exceptions/status.py
fastapi_http_exceptions/ws_exceptions.py
fastapi_http_exceptions-0.1.0.dist-info/METADATA
fastapi_http_exceptions-0.1.0.dist-info/WHEEL
fastapi_http_exceptions-0.1.0.dist-info/top_level.txt
fastapi_http_exceptions-0.1.0.dist-info/RECORD
