Metadata-Version: 2.2
Name: fastapi-http-exceptions
Version: 0.1.0
Summary: A library for handling HTTP exceptions in FastAPI applications, providing a set of predefined exceptions for common HTTP error statuses like 404, 403, 401, etc., to make error handling in APIs more streamlined and maintainable.
Author-email: Sebastian Sala <sebastian.sala.alanis@hotmail.com>
Project-URL: Homepage, https://github.com/sebasxsala/fastapi-http-exceptions
Project-URL: Bug Tracker, https://github.com/sebasxsala/fastapi-http-exceptions/issues
Requires-Python: >=3.9
Requires-Dist: fastapi>=0.115.0
